logical_rush/__init__.py
logical_rush/logical_rush.cp310-win_amd64.pyd
logical_rush-0.0.7.dist-info/METADATA
logical_rush-0.0.7.dist-info/WHEEL
logical_rush-0.0.7.dist-info/top_level.txt
logical_rush-0.0.7.dist-info/RECORD
