Metadata-Version: 2.1
Name: logical-rush
Version: 0.0.7
Summary: Batch-computing solution for cashflow calculations.
Author: Blasser Analytica (Rodolfo Blasser)
Author-email: <rodolfoblasser@gmail.com>
Keywords: batch-computing,cashflows,amortization
Classifier: Development Status :: 1 - Planning
Classifier: Intended Audience :: Developers
Classifier: Programming Language :: Python :: 3
Classifier: Operating System :: Microsoft :: Windows
Requires-Python: >=3.10
